{
  "type": "FeatureCollection",
  "features": [
    {
      "name": "Astor Pl",
      "line": "4-6-6 Express",
      "coords": [-73.99106999861966, 40.73005400028978],
      "type": "Point"
    },
    {
      "name": "Canal St",
      "line": "4-6-6 Express",
      "coords": [-74.00019299927328, 40.71880300107709],
      "type": "Point"
    },
    {
      "name": "50th St",
      "line": "1-2",
      "coords": [-73.98384899986625, 40.76172799961419],
      "type": "Point"
    },
    {
      "name": "Bergen St",
      "line": "2-3-4",
      "coords": [-73.97499915116808, 40.68086213682956],
      "type": "Point"
    },
    {
      "name": "Pennsylvania Ave",
      "line": "3-4",
      "coords": [-73.89488591154061, 40.66471445143568],
      "type": "Point"
    },
    {
      "name": "238th St",
      "line": "1",
      "coords": [-73.90087000018522, 40.88466700064975],
      "type": "Point"
    },
    {
      "name": "Cathedral Pkwy (110th St)",
      "line": "A-B-C",
      "coords": [-73.95806670661364, 40.800581558114956],
      "type": "Point"
    },
    {
      "name": "Kingston - Throop Aves",
      "line": "A-C",
      "coords": [-73.94085899871263, 40.67991899941601],
      "type": "Point"
    },
    {
      "name": "65th St",
      "line": "E-M-R",
      "coords": [-73.8987883783301, 40.74971952935675],
      "type": "Point"
    },
    {
      "name": "36th St",
      "line": "E-M-R",
      "coords": [-73.92901818461539, 40.75196004401078],
      "type": "Point"
    },
    {
      "name": "Delancey St - Essex St",
      "line": "J-M-Z",
      "coords": [-73.98740940202974, 40.71830605618619],
      "type": "Point"
    },
    {
      "name": "Van Siclen Ave",
      "line": "J-Z",
      "coords": [-73.89165772702445, 40.67802821447783],
      "type": "Point"
    },
    {
      "name": "Norwood Ave",
      "line": "J-Z",
      "coords": [-73.87962599910783, 40.68152000045683],
      "type": "Point"
    },
    {
      "name": "104th-102nd Sts",
      "line": "J-Z",
      "coords": [-73.84443500029684, 40.69516599823373],
      "type": "Point"
    },
    {
      "name": "DeKalb Ave",
      "line": "B-D-N-Q-R",
      "coords": [-73.98177094440949, 40.690648119969794],
      "type": "Point"
    },
    {
      "name": "Beach 105th St",
      "line": "A-S",
      "coords": [-73.82758075034528, 40.58326843810286],
      "type": "Point"
    },
    {
      "name": "Beach 90th St",
      "line": "A-S",
      "coords": [-73.81365140419632, 40.58809156457325],
      "type": "Point"
    },
    {
      "name": "Freeman St",
      "line": "2-5",
      "coords": [-73.89175225349464, 40.829987446384116],
      "type": "Point"
    },
    {
      "name": "Intervale Ave",
      "line": "2-5",
      "coords": [-73.89661738461646, 40.822142131170786],
      "type": "Point"
    },
    {
      "name": "182nd-183rd Sts",
      "line": "B-D",
      "coords": [-73.90074099998965, 40.85609299881864],
      "type": "Point"
    },
    {
      "name": "174th-175th Sts",
      "line": "B-D",
      "coords": [-73.91013600050078, 40.84589999983414],
      "type": "Point"
    },
    {
      "name": "167th St",
      "line": "B-D",
      "coords": [-73.91843200082253, 40.83376899862797],
      "type": "Point"
    },
    {
      "name": "Mets - Willets Point",
      "line": "7-7 Express",
      "coords": [-73.8456249984179, 40.75462199881262],
      "type": "Point"
    },
    {
      "name": "Junction Blvd",
      "line": "7-7 Express",
      "coords": [-73.86952700103515, 40.74914499948836],
      "type": "Point"
    },
    {
      "name": "Flushing - Main St",
      "line": "7-7 Express",
      "coords": [-73.83003000262508, 40.75959999915012],
      "type": "Point"
    },
    {
      "name": "Buhre Ave",
      "line": "6-6 Express",
      "coords": [-73.83256900003744, 40.846809998885504],
      "type": "Point"
    },
    {
      "name": "3rd Ave - 138th St",
      "line": "6-6 Express",
      "coords": [-73.92613800014134, 40.81047600117261],
      "type": "Point"
    },
    {
      "name": "Castle Hill Ave",
      "line": "6-6 Express",
      "coords": [-73.85122199961472, 40.83425499825462],
      "type": "Point"
    },
    {
      "name": "Brooklyn Bridge - City Hall",
      "line": "4-5-6-6 Express",
      "coords": [-74.0041310005885, 40.713064999433136],
      "type": "Point"
    },
    {
      "name": "Zerega Ave",
      "line": "6-6 Express",
      "coords": [-73.8470359987544, 40.836488000608156],
      "type": "Point"
    },
    {
      "name": "Grand Central - 42nd St",
      "line": "4-5-6-6 Express",
      "coords": [-73.9767132992584, 40.75180742981634],
      "type": "Point"
    },
    {
      "name": "33rd St",
      "line": "4-6-6 Express",
      "coords": [-73.98207600148947, 40.74608099909145],
      "type": "Point"
    },
    {
      "name": "96th St",
      "line": "4-6-6 Express",
      "coords": [-73.9510700015425, 40.78567199998607],
      "type": "Point"
    },
    {
      "name": "77th St",
      "line": "4-6-6 Express",
      "coords": [-73.95987399886047, 40.77362000074615],
      "type": "Point"
    },
    {
      "name": "Chauncey St",
      "line": "J-Z",
      "coords": [-73.91038357033376, 40.68285130087804],
      "type": "Point"
    },
    {
      "name": "Union St",
      "line": "D-N-R",
      "coords": [-73.98310999909673, 40.67731566735096],
      "type": "Point"
    },
    {
      "name": "Elmhurst Ave",
      "line": "E-M-R",
      "coords": [-73.8820347465864, 40.74237007972169],
      "type": "Point"
    },
    {
      "name": "Ralph Ave",
      "line": "A-C",
      "coords": [-73.92078599933306, 40.678822000873375],
      "type": "Point"
    },
    {
      "name": "Pelham Pkwy",
      "line": "2-5",
      "coords": [-73.86748067850041, 40.8571924091606],
      "type": "Point"
    },
    {
      "name": "Gun Hill Rd",
      "line": "2-5",
      "coords": [-73.86613410538703, 40.877839385172024],
      "type": "Point"
    },
    {
      "name": "Nereid Ave (238 St)",
      "line": "2-5",
      "coords": [-73.8543153107622, 40.898286515575286],
      "type": "Point"
    },
    {
      "name": "Franklin Ave",
      "line": "2-3-4-5",
      "coords": [-73.9580997367769, 40.67076515344894],
      "type": "Point"
    },
    {
      "name": "Simpson St",
      "line": "2-5",
      "coords": [-73.89306639507903, 40.823976841237396],
      "type": "Point"
    },
    {
      "name": "Bronx Park East",
      "line": "2-5",
      "coords": [-73.86835609178098, 40.848768666338934],
      "type": "Point"
    },
    {
      "name": "Winthrop St",
      "line": "2-5",
      "coords": [-73.95007934590994, 40.65665931376077],
      "type": "Point"
    },
    {
      "name": "Van Siclen Ave",
      "line": "3-4",
      "coords": [-73.88940491730106, 40.665517963059635],
      "type": "Point"
    },
    {
      "name": "149th St - Grand Concourse",
      "line": "4",
      "coords": [-73.9273847542618, 40.81830344372315],
      "type": "Point"
    },
    {
      "name": "161st St - Yankee Stadium",
      "line": "4",
      "coords": [-73.92569199505733, 40.82823032742169],
      "type": "Point"
    },
    {
      "name": "Lexington Ave - 59th St",
      "line": "4-5-6-6 Express",
      "coords": [-73.9679670004732, 40.762526000304575],
      "type": "Point"
    },
    {
      "name": "E 149th St",
      "line": "6",
      "coords": [-73.90409799875945, 40.81211799827203],
      "type": "Point"
    },
    {
      "name": "Morrison Av - Soundview",
      "line": "6",
      "coords": [-73.87451599929486, 40.82952100156747],
      "type": "Point"
    },
    {
      "name": "Whitlock Ave",
      "line": "6",
      "coords": [-73.8862829985325, 40.82652500055904],
      "type": "Point"
    },
    {
      "name": "St Lawrence Ave",
      "line": "6",
      "coords": [-73.86761799923673, 40.8315090005233],
      "type": "Point"
    },
    {
      "name": "Woodside - 61st St",
      "line": "7-7 Express",
      "coords": [-73.90298400173006, 40.745630001138395],
      "type": "Point"
    },
    {
      "name": "Far Rockaway - Mott Ave",
      "line": "A",
      "coords": [-73.75540499924732, 40.603995001687544],
      "type": "Point"
    },
    {
      "name": "72nd St",
      "line": "A-B-C",
      "coords": [-73.976336575218, 40.77551939729258],
      "type": "Point"
    },
    {
      "name": "96th St",
      "line": "A-B-C",
      "coords": [-73.96460245687166, 40.79161879767014],
      "type": "Point"
    },
    {
      "name": "168th St",
      "line": "A-C",
      "coords": [-73.93956099985425, 40.84071899990795],
      "type": "Point"
    },
    {
      "name": "Kingsbridge Rd",
      "line": "B-D",
      "coords": [-73.8935090000331, 40.86697799999945],
      "type": "Point"
    },
    {
      "name": "42nd St - Bryant Pk",
      "line": "B-D-F-M",
      "coords": [-73.98459099904711, 40.754184001312545],
      "type": "Point"
    },
    {
      "name": "Prospect Park",
      "line": "B-Q-S",
      "coords": [-73.96203130426609, 40.6616334551018],
      "type": "Point"
    },
    {
      "name": "55th St",
      "line": "D",
      "coords": [-73.99534882595742, 40.63147876093745],
      "type": "Point"
    },
    {
      "name": "Jamaica - Van Wyck",
      "line": "E",
      "coords": [-73.81701287135405, 40.70289855287313],
      "type": "Point"
    },
    {
      "name": "Kew Gardens - Union Tpke",
      "line": "E-F",
      "coords": [-73.8303702709878, 40.714034819571026],
      "type": "Point"
    },
    {
      "name": "Sutphin Blvd - Archer Av",
      "line": "E-J-Z",
      "coords": [-73.80800471963833, 40.700382424235],
      "type": "Point"
    },
    {
      "name": "Court Sq - 23rd St",
      "line": "E-M",
      "coords": [-73.94605470266329, 40.747768121414325],
      "type": "Point"
    },
    {
      "name": "67th Ave",
      "line": "E-M-R",
      "coords": [-73.85286048434907, 40.726505475813006],
      "type": "Point"
    },
    {
      "name": "Grand Ave - Newtown",
      "line": "E-M-R",
      "coords": [-73.87722085669182, 40.736813418197144],
      "type": "Point"
    },
    {
      "name": "Ditmas Ave",
      "line": "F",
      "coords": [-73.97817199965161, 40.63611866666291],
      "type": "Point"
    },
    {
      "name": "Classon Ave",
      "line": "G",
      "coords": [-73.95999000137212, 40.68888900026455],
      "type": "Point"
    },
    {
      "name": "Broadway",
      "line": "G",
      "coords": [-73.95031225606621, 40.706126576274166],
      "type": "Point"
    },
    {
      "name": "Lorimer St",
      "line": "L",
      "coords": [-73.95024799996972, 40.71407200064717],
      "type": "Point"
    },
    {
      "name": "Sutter Ave",
      "line": "L",
      "coords": [-73.9019160004208, 40.66914500061398],
      "type": "Point"
    },
    {
      "name": "Wilson Ave",
      "line": "L",
      "coords": [-73.90395860491864, 40.68886654246024],
      "type": "Point"
    },
    {
      "name": "Halsey St",
      "line": "J",
      "coords": [-73.9166388842194, 40.686415270704344],
      "type": "Point"
    },
    {
      "name": "Lorimer St",
      "line": "J-M",
      "coords": [-73.94735499884204, 40.703844000042096],
      "type": "Point"
    },
    {
      "name": "8th Ave",
      "line": "N",
      "coords": [-74.01151599772157, 40.634970999647166],
      "type": "Point"
    },
    {
      "name": "36th Ave",
      "line": "N-W",
      "coords": [-73.929861999118, 40.7564420005104],
      "type": "Point"
    },
    {
      "name": "Broadway",
      "line": "N-W",
      "coords": [-73.92582299919906, 40.761431998800546],
      "type": "Point"
    },
    {
      "name": "Times Sq - 42nd St",
      "line": "N-Q-R-W",
      "coords": [-73.98676800153976, 40.75461199851542],
      "type": "Point"
    },
    {
      "name": "Grand Central - 42nd St",
      "line": "S",
      "coords": [-73.97918899989101, 40.75276866674217],
      "type": "Point"
    },
    {
      "name": "Park Pl",
      "line": "S",
      "coords": [-73.95762400074634, 40.67477166685263],
      "type": "Point"
    },
    {
      "name": "111th St",
      "line": "A-S",
      "coords": [-73.83216299845388, 40.68433100001238],
      "type": "Point"
    },
    {
      "name": "W 4th St - Washington Sq (Lower)",
      "line": "B-D-F-M",
      "coords": [-74.00030814755975, 40.732254493367876],
      "type": "Point"
    },
    {
      "name": "51st St",
      "line": "4-6-6 Express",
      "coords": [-73.97192000069982, 40.75710699989316],
      "type": "Point"
    },
    {
      "name": "86th St",
      "line": "1-2",
      "coords": [-73.97621799859327, 40.78864400073892],
      "type": "Point"
    },
    {
      "name": "233rd St",
      "line": "2-5",
      "coords": [-73.85736239521543, 40.89314324138378],
      "type": "Point"
    },
    {
      "name": "66th St - Lincoln Ctr",
      "line": "1-2",
      "coords": [-73.98220899995783, 40.77344000052039],
      "type": "Point"
    },
    {
      "name": "Hunts Point Ave",
      "line": "6-6 Express",
      "coords": [-73.89054900017344, 40.82094799852307],
      "type": "Point"
    },
    {
      "name": "Canal St",
      "line": "1-2",
      "coords": [-74.0062770001748, 40.72285399778783],
      "type": "Point"
    },
    {
      "name": "Middletown Rd",
      "line": "6-6 Express",
      "coords": [-73.83632199755944, 40.84386300128381],
      "type": "Point"
    },
    {
      "name": "23rd St",
      "line": "4-6-6 Express",
      "coords": [-73.98659900207888, 40.739864000474604],
      "type": "Point"
    },
    {
      "name": "Court Sq",
      "line": "7-7 Express",
      "coords": [-73.94526400039679, 40.74702299889643],
      "type": "Point"
    },
    {
      "name": "59th St - Columbus Circle",
      "line": "1-2",
      "coords": [-73.98192900232715, 40.76824700063689],
      "type": "Point"
    },
    {
      "name": "Hunters Point Ave",
      "line": "7-7 Express",
      "coords": [-73.9489160009391, 40.74221599986316],
      "type": "Point"
    },
    {
      "name": "23rd St",
      "line": "1-2",
      "coords": [-73.9956570016487, 40.74408099989751],
      "type": "Point"
    },
    {
      "name": "Houston St",
      "line": "1-2",
      "coords": [-74.00536700180581, 40.728251000730204],
      "type": "Point"
    },
    {
      "name": "104th St",
      "line": "A-S",
      "coords": [-73.83768300060997, 40.681711001091195],
      "type": "Point"
    },
    {
      "name": "Broad Channel",
      "line": "A-S",
      "coords": [-73.81583268782963, 40.60840218069683],
      "type": "Point"
    },
    {
      "name": "Ocean Pkwy",
      "line": "Q",
      "coords": [-73.96850099975177, 40.57631166708091],
      "type": "Point"
    },
    {
      "name": "Vernon Blvd - Jackson Ave",
      "line": "7-7 Express",
      "coords": [-73.95358099875249, 40.74262599969749],
      "type": "Point"
    },
    {
      "name": "68th St - Hunter College",
      "line": "4-6-6 Express",
      "coords": [-73.96387000158042, 40.76814100049679],
      "type": "Point"
    },
    {
      "name": "Queensboro Plz",
      "line": "7-7 Express-N-W",
      "coords": [-73.9401635351909, 40.750635651014804],
      "type": "Point"
    },
    {
      "name": "Rockaway Blvd",
      "line": "A-S",
      "coords": [-73.8438529979573, 40.680428999588415],
      "type": "Point"
    },
    {
      "name": "Union Sq - 14th St",
      "line": "4-5-6-6 Express",
      "coords": [-73.98995099881881, 40.734673000996125],
      "type": "Point"
    },
    {
      "name": "Bedford - Nostrand Aves",
      "line": "G",
      "coords": [-73.95352200064022, 40.68962700158444],
      "type": "Point"
    },
    {
      "name": "15th St - Prospect Park",
      "line": "F-G",
      "coords": [-73.97973580592873, 40.66003568810021],
      "type": "Point"
    },
    {
      "name": "7th Ave",
      "line": "F-G",
      "coords": [-73.98025117900944, 40.66624469001985],
      "type": "Point"
    },
    {
      "name": "Ft Hamilton Pkwy",
      "line": "F-G",
      "coords": [-73.97577599917474, 40.65078166803418],
      "type": "Point"
    },
    {
      "name": "Church Ave",
      "line": "F-G",
      "coords": [-73.97972116229084, 40.64427200012998],
      "type": "Point"
    },
    {
      "name": "Beverly Rd",
      "line": "Q",
      "coords": [-73.96435779623125, 40.64390459860419],
      "type": "Point"
    },
    {
      "name": "Church Ave",
      "line": "B-Q",
      "coords": [-73.96288246192114, 40.65049324646484],
      "type": "Point"
    },
    {
      "name": "Newkirk Ave",
      "line": "B-Q",
      "coords": [-73.96269486837261, 40.63514193733789],
      "type": "Point"
    },
    {
      "name": "Parkside Ave",
      "line": "Q",
      "coords": [-73.96145343987648, 40.65507304163716],
      "type": "Point"
    },
    {
      "name": "Grand Army Plaza",
      "line": "2-3-4",
      "coords": [-73.9709563319228, 40.6752946951032],
      "type": "Point"
    },
    {
      "name": "Atlantic Av - Barclay's Center",
      "line": "2-3-4-5",
      "coords": [-73.97754993539385, 40.68442016526762],
      "type": "Point"
    },
    {
      "name": "Rockaway Ave",
      "line": "A-C",
      "coords": [-73.91194599726617, 40.678339999883505],
      "type": "Point"
    },
    {
      "name": "Fulton St",
      "line": "G",
      "coords": [-73.97537499833149, 40.68711899950771],
      "type": "Point"
    },
    {
      "name": "Clinton - Washington Aves",
      "line": "G",
      "coords": [-73.9667959986695, 40.68809400106055],
      "type": "Point"
    },
    {
      "name": "7th Ave",
      "line": "B-Q",
      "coords": [-73.97285279191024, 40.67710217983294],
      "type": "Point"
    },
    {
      "name": "Atlantic Av - Barclay's Center",
      "line": "B-Q",
      "coords": [-73.97678343963167, 40.684488323453685],
      "type": "Point"
    },
    {
      "name": "Atlantic Av - Barclay's Center",
      "line": "D-N-Q-R",
      "coords": [-73.97880999956767, 40.683665667279435],
      "type": "Point"
    },
    {
      "name": "Borough Hall",
      "line": "4-5",
      "coords": [-73.99015100090539, 40.692403999991036],
      "type": "Point"
    },
    {
      "name": "Aqueduct Racetrack",
      "line": "A",
      "coords": [-73.83591899965162, 40.672096999172844],
      "type": "Point"
    },
    {
      "name": "Morris Park",
      "line": "5",
      "coords": [-73.86049500117254, 40.85436399966426],
      "type": "Point"
    },
    {
      "name": "Pelham Pkwy",
      "line": "5",
      "coords": [-73.85535900043564, 40.858984999820116],
      "type": "Point"
    },
    {
      "name": "Nostrand Ave",
      "line": "A-C",
      "coords": [-73.95042600099683, 40.68043800006226],
      "type": "Point"
    },
    {
      "name": "Nevins St",
      "line": "2-3-4-5",
      "coords": [-73.98040679874578, 40.68831058019022],
      "type": "Point"
    },
    {
      "name": "Eastern Pkwy - Bklyn Museum",
      "line": "2-3-4",
      "coords": [-73.96422203748425, 40.67203223545925],
      "type": "Point"
    },
    {
      "name": "Beverly Rd",
      "line": "2-5",
      "coords": [-73.94884798381702, 40.64512351894373],
      "type": "Point"
    },
    {
      "name": "Church Ave",
      "line": "2-5",
      "coords": [-73.94945514035334, 40.6508606878022],
      "type": "Point"
    },
    {
      "name": "Newkirk Ave",
      "line": "2-5",
      "coords": [-73.94829990822407, 40.63999124275311],
      "type": "Point"
    },
    {
      "name": "Brooklyn College - Flatbush Ave",
      "line": "2-5",
      "coords": [-73.94754120734406, 40.63284240700742],
      "type": "Point"
    },
    {
      "name": "Sterling St",
      "line": "2-5",
      "coords": [-73.95072891124937, 40.6627729934283],
      "type": "Point"
    },
    {
      "name": "Crown Hts - Utica Ave",
      "line": "3-4",
      "coords": [-73.93293256081851, 40.66897831107809],
      "type": "Point"
    },
    {
      "name": "Kingston Ave",
      "line": "3-4",
      "coords": [-73.94215978392963, 40.66948144864978],
      "type": "Point"
    },
    {
      "name": "Nassau Ave",
      "line": "G",
      "coords": [-73.95118300016523, 40.724479997808274],
      "type": "Point"
    },
    {
      "name": "Greenpoint Ave",
      "line": "G",
      "coords": [-73.95442500146235, 40.73126699971465],
      "type": "Point"
    },
    {
      "name": "Marcy Ave",
      "line": "J-M-Z",
      "coords": [-73.95783200075729, 40.708383000017925],
      "type": "Point"
    },
    {
      "name": "Hewes St",
      "line": "J-M",
      "coords": [-73.95348800038457, 40.706889998054],
      "type": "Point"
    },
    {
      "name": "138th St - Grand Concourse",
      "line": "4-5",
      "coords": [-73.92984899935611, 40.81322399958908],
      "type": "Point"
    },
    {
      "name": "5th Ave - 53rd St",
      "line": "E-M",
      "coords": [-73.9752485052734, 40.76008683231326],
      "type": "Point"
    },
    {
      "name": "Lexington Ave - 53rd St",
      "line": "E-M",
      "coords": [-73.96907237490204, 40.75746830782865],
      "type": "Point"
    },
    {
      "name": "28th St",
      "line": "N-Q-R-W",
      "coords": [-73.98869800128737, 40.74545399979951],
      "type": "Point"
    },
    {
      "name": "Herald Sq - 34th St",
      "line": "N-Q-R-W",
      "coords": [-73.9879368338264, 40.74964456009442],
      "type": "Point"
    },
    {
      "name": "1st Ave",
      "line": "L",
      "coords": [-73.98168087489128, 40.73097497580066],
      "type": "Point"
    },
    {
      "name": "Times Sq - 42nd St",
      "line": "S",
      "coords": [-73.98622899953202, 40.755983000570076],
      "type": "Point"
    },
    {
      "name": "Metropolitan Ave",
      "line": "G",
      "coords": [-73.9514239994525, 40.71277400073426],
      "type": "Point"
    },
    {
      "name": "Grand St",
      "line": "L",
      "coords": [-73.94049699874644, 40.71157600064823],
      "type": "Point"
    },
    {
      "name": "Graham Ave",
      "line": "L",
      "coords": [-73.94394399869037, 40.714575998363635],
      "type": "Point"
    },
    {
      "name": "Bedford Ave",
      "line": "L",
      "coords": [-73.95666499806525, 40.71717399858899],
      "type": "Point"
    },
    {
      "name": "Montrose Ave",
      "line": "L",
      "coords": [-73.93979284713505, 40.70739106438455],
      "type": "Point"
    },
    {
      "name": "Long Island City - Court Sq",
      "line": "G",
      "coords": [-73.94381559597835, 40.74630503357145],
      "type": "Point"
    },
    {
      "name": "21st St",
      "line": "G",
      "coords": [-73.9495999997552, 40.7441286664954],
      "type": "Point"
    },
    {
      "name": "39th Ave",
      "line": "N-W",
      "coords": [-73.93285137679598, 40.75276306140845],
      "type": "Point"
    },
    {
      "name": "145th St",
      "line": "1",
      "coords": [-73.95035999879713, 40.82655099962194],
      "type": "Point"
    },
    {
      "name": "157th St",
      "line": "1",
      "coords": [-73.94488999901047, 40.8340410001399],
      "type": "Point"
    },
    {
      "name": "96th St",
      "line": "1-2-3",
      "coords": [-73.97232299915696, 40.79391900121471],
      "type": "Point"
    },
    {
      "name": "103rd St",
      "line": "1",
      "coords": [-73.96837899960818, 40.799446000334825],
      "type": "Point"
    },
    {
      "name": "Central Park North (110th St)",
      "line": "2-3",
      "coords": [-73.95182200176913, 40.79907499977324],
      "type": "Point"
    },
    {
      "name": "103rd St",
      "line": "A-B-C",
      "coords": [-73.96137008267617, 40.796060739904526],
      "type": "Point"
    },
    {
      "name": "72nd St",
      "line": "1-2-3",
      "coords": [-73.98197000159583, 40.77845300068614],
      "type": "Point"
    },
    {
      "name": "81st St",
      "line": "A-B-C",
      "coords": [-73.97209794937208, 40.78134608418206],
      "type": "Point"
    },
    {
      "name": "75th Ave",
      "line": "E-F",
      "coords": [-73.83692369387158, 40.71804465348743],
      "type": "Point"
    },
    {
      "name": "86th St",
      "line": "A-B-C",
      "coords": [-73.96882849429672, 40.78582304678557],
      "type": "Point"
    },
    {
      "name": "Cathedral Pkwy (110th St)",
      "line": "1",
      "coords": [-73.9668470005456, 40.80396699961484],
      "type": "Point"
    },
    {
      "name": "116th St - Columbia University",
      "line": "1",
      "coords": [-73.96410999757751, 40.807722001230864],
      "type": "Point"
    },
    {
      "name": "125th St",
      "line": "2-3",
      "coords": [-73.94549500011411, 40.807753999182815],
      "type": "Point"
    },
    {
      "name": "135th St",
      "line": "2-3",
      "coords": [-73.94077000106708, 40.8142290003391],
      "type": "Point"
    },
    {
      "name": "116th St",
      "line": "2-3",
      "coords": [-73.94962500096905, 40.802097999133004],
      "type": "Point"
    },
    {
      "name": "Tremont Ave",
      "line": "B-D",
      "coords": [-73.90522700122354, 40.850409999510234],
      "type": "Point"
    },
    {
      "name": "137th St - City College",
      "line": "1",
      "coords": [-73.95367600087873, 40.82200799968475],
      "type": "Point"
    },
    {
      "name": "145th St",
      "line": "3",
      "coords": [-73.93624499873299, 40.82042099969279],
      "type": "Point"
    },
    {
      "name": "176th St",
      "line": "4",
      "coords": [-73.91179399884471, 40.8484800012369],
      "type": "Point"
    },
    {
      "name": "Burnside Ave",
      "line": "4",
      "coords": [-73.9076840015997, 40.85345300155693],
      "type": "Point"
    },
    {
      "name": "170th St",
      "line": "B-D",
      "coords": [-73.91339999846983, 40.83930599964156],
      "type": "Point"
    },
    {
      "name": "168th St",
      "line": "1",
      "coords": [-73.94013299907257, 40.840555999148535],
      "type": "Point"
    },
    {
      "name": "181st St",
      "line": "1",
      "coords": [-73.9335959996056, 40.84950499974065],
      "type": "Point"
    },
    {
      "name": "191st St",
      "line": "1",
      "coords": [-73.92941199742039, 40.85522500175836],
      "type": "Point"
    },
    {
      "name": "175th St",
      "line": "A",
      "coords": [-73.93970399761596, 40.84739100072403],
      "type": "Point"
    },
    {
      "name": "Beach 44th St",
      "line": "A",
      "coords": [-73.77601299999507, 40.59294299908617],
      "type": "Point"
    },
    {
      "name": "Beach 60th St",
      "line": "A",
      "coords": [-73.7885219980118, 40.59237400121235],
      "type": "Point"
    },
    {
      "name": "Beach 98th St",
      "line": "A-S",
      "coords": [-73.82052058959523, 40.58538569133279],
      "type": "Point"
    },
    {
      "name": "Rockaway Park - Beach 116 St",
      "line": "A-S",
      "coords": [-73.83559008701239, 40.580955865573515],
      "type": "Point"
    },
    {
      "name": "Beach 36th St",
      "line": "A",
      "coords": [-73.76817499939688, 40.59539800166876],
      "type": "Point"
    },
    {
      "name": "Beach 25th St",
      "line": "A",
      "coords": [-73.76135299762073, 40.60006600105881],
      "type": "Point"
    },
    {
      "name": "Parsons Blvd",
      "line": "F",
      "coords": [-73.80328900021885, 40.707571999615695],
      "type": "Point"
    },
    {
      "name": "169th St",
      "line": "F",
      "coords": [-73.79347419927721, 40.710517502784],
      "type": "Point"
    },
    {
      "name": "103rd St - Corona Plaza",
      "line": "7",
      "coords": [-73.86269999830412, 40.749865000555545],
      "type": "Point"
    },
    {
      "name": "111th St",
      "line": "7",
      "coords": [-73.85533399834884, 40.75172999941711],
      "type": "Point"
    },
    {
      "name": "63rd Dr - Rego Park",
      "line": "E-M-R",
      "coords": [-73.86161820097203, 40.729763972422425],
      "type": "Point"
    },
    {
      "name": "Grant Ave",
      "line": "A-S",
      "coords": [-73.86504999877702, 40.67704400054478],
      "type": "Point"
    },
    {
      "name": "79th St",
      "line": "1-2",
      "coords": [-73.97991700056134, 40.78393399959032],
      "type": "Point"
    },
    {
      "name": "Atlantic Ave",
      "line": "L",
      "coords": [-73.9030969995401, 40.67534466640805],
      "type": "Point"
    },
    {
      "name": "Christopher St - Sheridan Sq",
      "line": "1-2",
      "coords": [-74.00290599855235, 40.73342200104225],
      "type": "Point"
    },
    {
      "name": "Ozone Park - Lefferts Blvd",
      "line": "A-S",
      "coords": [-73.82579799906613, 40.68595099878361],
      "type": "Point"
    },
    {
      "name": "Times Sq - 42nd St",
      "line": "7-7 Express",
      "coords": [-73.98769099825152, 40.755477001982506],
      "type": "Point"
    },
    {
      "name": "W 8th St - NY Aquarium",
      "line": "F-Q",
      "coords": [-73.97595787413822, 40.576033818103646],
      "type": "Point"
    },
    {
      "name": "28th St",
      "line": "1-2",
      "coords": [-73.99336500134324, 40.74721499918219],
      "type": "Point"
    },
    {
      "name": "28th St",
      "line": "4-6-6 Express",
      "coords": [-73.98426400110407, 40.743069999259035],
      "type": "Point"
    },
    {
      "name": "Pelham Bay Park",
      "line": "6-6 Express",
      "coords": [-73.82812100059289, 40.85246199951662],
      "type": "Point"
    },
    {
      "name": "Westchester Sq - E Tremont Ave",
      "line": "6-6 Express",
      "coords": [-73.84295199925012, 40.839892001013915],
      "type": "Point"
    },
    {
      "name": "18th St",
      "line": "1-2",
      "coords": [-73.99787100060406, 40.741039999802105],
      "type": "Point"
    },
    {
      "name": "Grand Central - 42nd St",
      "line": "7-7 Express",
      "coords": [-73.97604100111508, 40.751431000286864],
      "type": "Point"
    },
    {
      "name": "Beach 67th St",
      "line": "A",
      "coords": [-73.7969239998421, 40.59092700078133],
      "type": "Point"
    },
    {
      "name": "W 4th St - Washington Sq (Upper)",
      "line": "A-C-E",
      "coords": [-74.00049500225435, 40.73233799774325],
      "type": "Point"
    },
    {
      "name": "85th St - Forest Pky",
      "line": "J",
      "coords": [-73.86008700006875, 40.69242699966103],
      "type": "Point"
    },
    {
      "name": "Woodhaven Blvd",
      "line": "J-Z",
      "coords": [-73.85205199740794, 40.69370399880105],
      "type": "Point"
    },
    {
      "name": "111th St",
      "line": "J",
      "coords": [-73.83679338454697, 40.697114810696476],
      "type": "Point"
    },
    {
      "name": "121st St",
      "line": "J-Z",
      "coords": [-73.82834900017954, 40.700481998515315],
      "type": "Point"
    },
    {
      "name": "Halsey St",
      "line": "L",
      "coords": [-73.90393400118631, 40.69551800114878],
      "type": "Point"
    },
    {
      "name": "Myrtle - Wyckoff Aves",
      "line": "L",
      "coords": [-73.9109757182647, 40.699471062427136],
      "type": "Point"
    },
    {
      "name": "New Lots Ave",
      "line": "3-4",
      "coords": [-73.88411070800329, 40.6663149325969],
      "type": "Point"
    },
    {
      "name": "Van Siclen Ave",
      "line": "A-C",
      "coords": [-73.8903580002471, 40.67270999906104],
      "type": "Point"
    },
    {
      "name": "Cleveland St",
      "line": "J",
      "coords": [-73.8851940021643, 40.679777998961164],
      "type": "Point"
    },
    {
      "name": "Livonia Ave",
      "line": "L",
      "coords": [-73.90056237226057, 40.66405727094644],
      "type": "Point"
    },
    {
      "name": "Junius St",
      "line": "3-4",
      "coords": [-73.90244864183562, 40.66358900181724],
      "type": "Point"
    },
    {
      "name": "Rockaway Ave",
      "line": "3-4",
      "coords": [-73.90895833584449, 40.66261748815223],
      "type": "Point"
    },
    {
      "name": "Canarsie - Rockaway Pkwy",
      "line": "L",
      "coords": [-73.90185000017287, 40.64665366739528],
      "type": "Point"
    },
    {
      "name": "E 105th St",
      "line": "L",
      "coords": [-73.89954769388724, 40.65046878544699],
      "type": "Point"
    },
    {
      "name": "Saratoga Ave",
      "line": "3-4",
      "coords": [-73.91633025007947, 40.6615297898075],
      "type": "Point"
    },
    {
      "name": "Sutter Ave - Rutland Road",
      "line": "3-4",
      "coords": [-73.92252118536001, 40.66476678877493],
      "type": "Point"
    },
    {
      "name": "New Lots Ave",
      "line": "L",
      "coords": [-73.89927796057142, 40.65891477368527],
      "type": "Point"
    },
    {
      "name": "Broadway Junction",
      "line": "J-Z",
      "coords": [-73.90428999746412, 40.67936600147369],
      "type": "Point"
    },
    {
      "name": "Alabama Ave",
      "line": "J",
      "coords": [-73.89852600159652, 40.676998000003756],
      "type": "Point"
    },
    {
      "name": "Shepherd Ave",
      "line": "A-C",
      "coords": [-73.88074999747269, 40.6741300014559],
      "type": "Point"
    },
    {
      "name": "Crescent St",
      "line": "J-Z",
      "coords": [-73.87392925215778, 40.68315265707736],
      "type": "Point"
    },
    {
      "name": "Cypress Hills",
      "line": "J",
      "coords": [-73.87332199882995, 40.689616000838754],
      "type": "Point"
    },
    {
      "name": "75th St - Eldert Ln",
      "line": "J-Z",
      "coords": [-73.86728799944963, 40.691290001246735],
      "type": "Point"
    },
    {
      "name": "69th St",
      "line": "7",
      "coords": [-73.8964029993185, 40.746324999410284],
      "type": "Point"
    },
    {
      "name": "74th St - Broadway",
      "line": "7",
      "coords": [-73.8912051289911, 40.746867573829114],
      "type": "Point"
    },
    {
      "name": "Woodhaven Blvd - Queens Mall",
      "line": "E-M-R",
      "coords": [-73.86943208612348, 40.73309737380972],
      "type": "Point"
    },
    {
      "name": "Myrtle - Wyckoff Aves",
      "line": "M",
      "coords": [-73.91217899939602, 40.69945400090837],
      "type": "Point"
    },
    {
      "name": "Seneca Ave",
      "line": "M",
      "coords": [-73.90758199885423, 40.70291899894902],
      "type": "Point"
    },
    {
      "name": "DeKalb Ave",
      "line": "L",
      "coords": [-73.91823200219723, 40.70369299961644],
      "type": "Point"
    },
    {
      "name": "52nd St",
      "line": "7",
      "coords": [-73.91254899891254, 40.744149001021576],
      "type": "Point"
    },
    {
      "name": "46th St",
      "line": "E-M-R",
      "coords": [-73.91352174995538, 40.756316952608096],
      "type": "Point"
    },
    {
      "name": "Northern Blvd",
      "line": "E-M-R",
      "coords": [-73.90606508052358, 40.752824829236076],
      "type": "Point"
    },
    {
      "name": "46th St",
      "line": "7",
      "coords": [-73.91843500103973, 40.74313200060382],
      "type": "Point"
    },
    {
      "name": "82nd St - Jackson Hts",
      "line": "7",
      "coords": [-73.88369700071884, 40.747658999559135],
      "type": "Point"
    },
    {
      "name": "90th St - Elmhurst Av",
      "line": "7",
      "coords": [-73.87661299986985, 40.74840800060913],
      "type": "Point"
    },
    {
      "name": "Howard Beach - JFK Airport",
      "line": "A",
      "coords": [-73.83030100071032, 40.66047600004959],
      "type": "Point"
    },
    {
      "name": "Aqueduct - North Conduit Av",
      "line": "A",
      "coords": [-73.83405799948723, 40.668234001699815],
      "type": "Point"
    },
    {
      "name": "Briarwood - Van Wyck Blvd",
      "line": "E-F",
      "coords": [-73.82069263637443, 40.70916181536946],
      "type": "Point"
    },
    {
      "name": "Forest Hills - 71st Av",
      "line": "E-F-M-R",
      "coords": [-73.84451672012669, 40.72159430953587],
      "type": "Point"
    },
    {
      "name": "Sutphin Blvd",
      "line": "F",
      "coords": [-73.81083299897232, 40.70541799906764],
      "type": "Point"
    },
    {
      "name": "Jamaica Ctr - Parsons / Archer",
      "line": "E-J-Z",
      "coords": [-73.80109632298924, 40.70206737621188],
      "type": "Point"
    },
    {
      "name": "225th St",
      "line": "2-5",
      "coords": [-73.86021461772737, 40.88802825863786],
      "type": "Point"
    },
    {
      "name": "Elder Ave",
      "line": "6",
      "coords": [-73.87915899874777, 40.82858400108929],
      "type": "Point"
    },
    {
      "name": "Longwood Ave",
      "line": "6",
      "coords": [-73.89643499897414, 40.816103999972405],
      "type": "Point"
    },
    {
      "name": "Astoria Blvd",
      "line": "N-W",
      "coords": [-73.91809500109238, 40.77003699949086],
      "type": "Point"
    },
    {
      "name": "Astoria - Ditmars Blvd",
      "line": "N-W",
      "coords": [-73.9120340001031, 40.775035666523664],
      "type": "Point"
    },
    {
      "name": "Jackson Ave",
      "line": "2-5",
      "coords": [-73.9077019387083, 40.81643746686396],
      "type": "Point"
    },
    {
      "name": "Prospect Ave",
      "line": "2-5",
      "coords": [-73.90177778730917, 40.81948726483844],
      "type": "Point"
    },
    {
      "name": "Cypress Ave",
      "line": "6",
      "coords": [-73.91404199994753, 40.8053680007636],
      "type": "Point"
    },
    {
      "name": "174th St",
      "line": "2-5",
      "coords": [-73.88769359812888, 40.837195550170605],
      "type": "Point"
    },
    {
      "name": "Allerton Ave",
      "line": "2-5",
      "coords": [-73.86723422851625, 40.86548337793927],
      "type": "Point"
    },
    {
      "name": "E 143rd St - St Mary's St",
      "line": "6",
      "coords": [-73.90765699936489, 40.80871900090143],
      "type": "Point"
    },
    {
      "name": "Kingsbridge Rd",
      "line": "4",
      "coords": [-73.89717400101743, 40.867760000885795],
      "type": "Point"
    },
    {
      "name": "Bedford Park Blvd - Lehman College",
      "line": "4",
      "coords": [-73.89006400069478, 40.87341199980121],
      "type": "Point"
    },
    {
      "name": "Harlem - 148 St",
      "line": "3",
      "coords": [-73.93647000005559, 40.82388000080457],
      "type": "Point"
    },
    {
      "name": "Mt Eden Ave",
      "line": "4",
      "coords": [-73.9146849986034, 40.84443400092679],
      "type": "Point"
    },
    {
      "name": "Fordham Rd",
      "line": "B-D",
      "coords": [-73.89774900102401, 40.861295998683495],
      "type": "Point"
    },
    {
      "name": "170th St",
      "line": "4",
      "coords": [-73.91779099745928, 40.84007499993004],
      "type": "Point"
    },
    {
      "name": "Bedford Park Blvd",
      "line": "B-D",
      "coords": [-73.88713799889574, 40.87324399861646],
      "type": "Point"
    },
    {
      "name": "Marble Hill - 225th St",
      "line": "1",
      "coords": [-73.90983099923551, 40.87456099941789],
      "type": "Point"
    },
    {
      "name": "231st St",
      "line": "1",
      "coords": [-73.90483400107873, 40.87885599817935],
      "type": "Point"
    },
    {
      "name": "215th St",
      "line": "1",
      "coords": [-73.91527899954356, 40.86944399946045],
      "type": "Point"
    },
    {
      "name": "207th St",
      "line": "1",
      "coords": [-73.91881900132312, 40.864614000525854],
      "type": "Point"
    },
    {
      "name": "Inwood - 207th St",
      "line": "A",
      "coords": [-73.91989900100465, 40.86807199999737],
      "type": "Point"
    },
    {
      "name": "Van Cortlandt Park - 242nd St",
      "line": "1",
      "coords": [-73.89858300049647, 40.88924800011476],
      "type": "Point"
    },
    {
      "name": "West Farms Sq - E Tremont Av",
      "line": "2-5",
      "coords": [-73.87996127877184, 40.84020763241799],
      "type": "Point"
    },
    {
      "name": "219th St",
      "line": "2-5",
      "coords": [-73.8625097078866, 40.883887974625274],
      "type": "Point"
    },
    {
      "name": "Mosholu Pkwy",
      "line": "4",
      "coords": [-73.88465499988732, 40.87974999947229],
      "type": "Point"
    },
    {
      "name": "Norwood - 205th St",
      "line": "D",
      "coords": [-73.87885499918691, 40.87481100011182],
      "type": "Point"
    },
    {
      "name": "Burke Ave",
      "line": "2-5",
      "coords": [-73.86705361747603, 40.87125880254771],
      "type": "Point"
    },
    {
      "name": "Baychester Ave",
      "line": "5",
      "coords": [-73.83859099802153, 40.87866300037311],
      "type": "Point"
    },
    {
      "name": "Eastchester - Dyre Ave",
      "line": "5",
      "coords": [-73.8308340021742, 40.88829999901007],
      "type": "Point"
    },
    {
      "name": "Jamaica - 179th St",
      "line": "F",
      "coords": [-73.78381700176453, 40.712645666744045],
      "type": "Point"
    },
    {
      "name": "Wakefield - 241st St",
      "line": "2",
      "coords": [-73.8506199987954, 40.903125000541245],
      "type": "Point"
    },
    {
      "name": "Botanic Garden",
      "line": "S",
      "coords": [-73.95924499945693, 40.670342666584396],
      "type": "Point"
    },
    {
      "name": "Bushwick - Aberdeen",
      "line": "L",
      "coords": [-73.90526176305106, 40.68286062551184],
      "type": "Point"
    },
    {
      "name": "Broadway Junction",
      "line": "L",
      "coords": [-73.90311757920684, 40.67845624842869],
      "type": "Point"
    },
    {
      "name": "Gun Hill Rd",
      "line": "5",
      "coords": [-73.84638400151765, 40.86952599962676],
      "type": "Point"
    },
    {
      "name": "E 180th St",
      "line": "2-5",
      "coords": [-73.87334609510884, 40.8418630412186],
      "type": "Point"
    },
    {
      "name": "Dyckman St",
      "line": "1",
      "coords": [-73.92553600006474, 40.86053100138796],
      "type": "Point"
    },
    {
      "name": "125th St",
      "line": "1",
      "coords": [-73.95837200097044, 40.815580999978934],
      "type": "Point"
    },
    {
      "name": "Franklin Ave - Fulton St",
      "line": "S",
      "coords": [-73.95582700110425, 40.68059566598263],
      "type": "Point"
    },
    {
      "name": "149th St - Grand Concourse",
      "line": "2-5",
      "coords": [-73.92672247438611, 40.81833014409742],
      "type": "Point"
    },
    {
      "name": "3rd Ave - 149th St",
      "line": "2-5",
      "coords": [-73.91779152760981, 40.816029252510006],
      "type": "Point"
    },
    {
      "name": "167th St",
      "line": "4",
      "coords": [-73.92139999784426, 40.83553699933672],
      "type": "Point"
    },
    {
      "name": "Brook Ave",
      "line": "6",
      "coords": [-73.91923999909432, 40.80756599987699],
      "type": "Point"
    },
    {
      "name": "33rd St",
      "line": "7",
      "coords": [-73.93099699953838, 40.74458699983993],
      "type": "Point"
    },
    {
      "name": "40th St",
      "line": "7",
      "coords": [-73.9240159984882, 40.74378100149132],
      "type": "Point"
    },
    {
      "name": "145th St",
      "line": "A-B-C-D",
      "coords": [-73.94408792823116, 40.824766360871905],
      "type": "Point"
    },
    {
      "name": "155th St",
      "line": "B-D",
      "coords": [-73.93820899811622, 40.8301349999812],
      "type": "Point"
    },
    {
      "name": "161st St - Yankee Stadium",
      "line": "B-D",
      "coords": [-73.92565099775477, 40.827904998845845],
      "type": "Point"
    },
    {
      "name": "Utica Ave",
      "line": "A-C",
      "coords": [-73.93072899914027, 40.67936399950546],
      "type": "Point"
    },
    {
      "name": "Steinway St",
      "line": "E-M-R",
      "coords": [-73.9205264716827, 40.75698735912575],
      "type": "Point"
    },
    {
      "name": "Kosciuszko St",
      "line": "J",
      "coords": [-73.92850899927413, 40.69317200129202],
      "type": "Point"
    },
    {
      "name": "Gates Ave",
      "line": "J-Z",
      "coords": [-73.92215600150752, 40.689583999013905],
      "type": "Point"
    },
    {
      "name": "Central Ave",
      "line": "M",
      "coords": [-73.92724299902838, 40.69787300011831],
      "type": "Point"
    },
    {
      "name": "Knickerbocker Ave",
      "line": "M",
      "coords": [-73.91972000188625, 40.69866000123805],
      "type": "Point"
    },
    {
      "name": "30th Ave",
      "line": "N-W",
      "coords": [-73.9214790001739, 40.76677866673298],
      "type": "Point"
    },
    {
      "name": "Jefferson St",
      "line": "L",
      "coords": [-73.9229130000312, 40.706606665988716],
      "type": "Point"
    },
    {
      "name": "Morgan Ave",
      "line": "L",
      "coords": [-73.93314700024209, 40.70615166680729],
      "type": "Point"
    },
    {
      "name": "Queens Plz",
      "line": "E-M-R",
      "coords": [-73.93713823965695, 40.74891771986323],
      "type": "Point"
    },
    {
      "name": "18th Ave",
      "line": "F",
      "coords": [-73.97697099965796, 40.62975466638584],
      "type": "Point"
    },
    {
      "name": "77th St",
      "line": "R",
      "coords": [-74.0255099996266, 40.629741666886915],
      "type": "Point"
    },
    {
      "name": "Bay Ridge Ave",
      "line": "R",
      "coords": [-74.02337699950728, 40.63496666682377],
      "type": "Point"
    },
    {
      "name": "50th St",
      "line": "D",
      "coords": [-73.9946587805514, 40.636260890961395],
      "type": "Point"
    },
    {
      "name": "Ft Hamilton Pkwy",
      "line": "N",
      "coords": [-74.00535100046275, 40.63138566722445],
      "type": "Point"
    },
    {
      "name": "25th Ave",
      "line": "D",
      "coords": [-73.98682900011477, 40.59770366695856],
      "type": "Point"
    },
    {
      "name": "Bay Pky",
      "line": "D",
      "coords": [-73.9936762000529, 40.601950461572315],
      "type": "Point"
    },
    {
      "name": "20th Ave",
      "line": "N",
      "coords": [-73.98452199846113, 40.617108999866005],
      "type": "Point"
    },
    {
      "name": "18th Ave",
      "line": "N",
      "coords": [-73.99045399865993, 40.620686997680025],
      "type": "Point"
    },
    {
      "name": "Bay Ridge - 95th St",
      "line": "R",
      "coords": [-74.03087600085765, 40.61662166725951],
      "type": "Point"
    },
    {
      "name": "86th St",
      "line": "R",
      "coords": [-74.0283979999864, 40.62268666715025],
      "type": "Point"
    },
    {
      "name": "79th St",
      "line": "D",
      "coords": [-74.00058287431507, 40.61315892569516],
      "type": "Point"
    },
    {
      "name": "71st St",
      "line": "D",
      "coords": [-73.99884094850685, 40.61925870977273],
      "type": "Point"
    },
    {
      "name": "20th Ave",
      "line": "D",
      "coords": [-73.99817432157568, 40.60467699816932],
      "type": "Point"
    },
    {
      "name": "18th Ave",
      "line": "D",
      "coords": [-74.00159259239406, 40.60773573171741],
      "type": "Point"
    },
    {
      "name": "62nd St",
      "line": "D",
      "coords": [-73.99685724994863, 40.626224462922195],
      "type": "Point"
    },
    {
      "name": "New Utrecht Ave",
      "line": "N",
      "coords": [-73.99635300025969, 40.62484166725887],
      "type": "Point"
    },
    {
      "name": "Ave U",
      "line": "F",
      "coords": [-73.97337641974885, 40.59592482551748],
      "type": "Point"
    },
    {
      "name": "Kings Hwy",
      "line": "F",
      "coords": [-73.9723553085244, 40.603258405128265],
      "type": "Point"
    },
    {
      "name": "Brighton Beach",
      "line": "B-Q",
      "coords": [-73.96135378598797, 40.577710196642435],
      "type": "Point"
    },
    {
      "name": "Sheepshead Bay",
      "line": "B-Q",
      "coords": [-73.95405791257907, 40.58654754707536],
      "type": "Point"
    },
    {
      "name": "Ave U",
      "line": "Q",
      "coords": [-73.95581122316301, 40.59930895095475],
      "type": "Point"
    },
    {
      "name": "Kings Hwy",
      "line": "B-Q",
      "coords": [-73.95760873538083, 40.608638645396006],
      "type": "Point"
    },
    {
      "name": "Ave U",
      "line": "N",
      "coords": [-73.97908400099428, 40.597235999920436],
      "type": "Point"
    },
    {
      "name": "Kings Hwy",
      "line": "N",
      "coords": [-73.98037300229343, 40.60405899980493],
      "type": "Point"
    },
    {
      "name": "Neptune Ave",
      "line": "F",
      "coords": [-73.97459272818807, 40.580738758491464],
      "type": "Point"
    },
    {
      "name": "Ave X",
      "line": "F",
      "coords": [-73.97426599968905, 40.589449666625285],
      "type": "Point"
    },
    {
      "name": "Bay 50th St",
      "line": "D",
      "coords": [-73.98376500045946, 40.58884066651933],
      "type": "Point"
    },
    {
      "name": "Gravesend - 86th St",
      "line": "N",
      "coords": [-73.97818899936274, 40.59246500088859],
      "type": "Point"
    },
    {
      "name": "Ave P",
      "line": "F",
      "coords": [-73.97300281528751, 40.608842808949916],
      "type": "Point"
    },
    {
      "name": "Ave N",
      "line": "F",
      "coords": [-73.97404850873143, 40.61435671190883],
      "type": "Point"
    },
    {
      "name": "Bay Pky",
      "line": "F",
      "coords": [-73.9752569782215, 40.62073162316788],
      "type": "Point"
    },
    {
      "name": "Ave M",
      "line": "Q",
      "coords": [-73.9592431052215, 40.617397744443736],
      "type": "Point"
    },
    {
      "name": "Bay Pky",
      "line": "N",
      "coords": [-73.98178001069293, 40.61145578989005],
      "type": "Point"
    },
    {
      "name": "Ave I",
      "line": "F",
      "coords": [-73.97606933170925, 40.62501744019143],
      "type": "Point"
    },
    {
      "name": "Ave J",
      "line": "Q",
      "coords": [-73.96069316246925, 40.625022819915166],
      "type": "Point"
    },
    {
      "name": "Ave H",
      "line": "Q",
      "coords": [-73.96151793942495, 40.62920837758969],
      "type": "Point"
    },
    {
      "name": "Neck Rd",
      "line": "Q",
      "coords": [-73.95507827493762, 40.59532169111695],
      "type": "Point"
    },
    {
      "name": "21st St - Queensbridge",
      "line": "F",
      "coords": [-73.94193761457447, 40.75373927087553],
      "type": "Point"
    },
    {
      "name": "50th St",
      "line": "A-C-E",
      "coords": [-73.98598400026407, 40.76245599925997],
      "type": "Point"
    },
    {
      "name": "7th Ave",
      "line": "B-D-E",
      "coords": [-73.98169782344476, 40.76297015245628],
      "type": "Point"
    },
    {
      "name": "47th-50th Sts - Rockefeller Ctr",
      "line": "B-D-F-M",
      "coords": [-73.98133100227702, 40.75864100159815],
      "type": "Point"
    },
    {
      "name": "57th St",
      "line": "F",
      "coords": [-73.97736800085171, 40.76408500081713],
      "type": "Point"
    },
    {
      "name": "Lexington Ave - 63rd St",
      "line": "F-Q",
      "coords": [-73.96608964413245, 40.76461809442373],
      "type": "Point"
    },
    {
      "name": "Roosevelt Island - Main St",
      "line": "F",
      "coords": [-73.95323499978866, 40.75917199967108],
      "type": "Point"
    },
    {
      "name": "59th St - Columbus Circle",
      "line": "A-B-C-D",
      "coords": [-73.98164872301398, 40.768249531776064],
      "type": "Point"
    },
    {
      "name": "49th St",
      "line": "N-Q-R-W",
      "coords": [-73.98420956591096, 40.759801973870694],
      "type": "Point"
    },
    {
      "name": "57th St",
      "line": "N-Q-R-W",
      "coords": [-73.98072973372128, 40.76456552501829],
      "type": "Point"
    },
    {
      "name": "5th Ave - 59th St",
      "line": "N-R-W",
      "coords": [-73.97334700047045, 40.764810999755284],
      "type": "Point"
    },
    {
      "name": "Lexington Ave - 59th St",
      "line": "N-R-W",
      "coords": [-73.96737501711436, 40.762708855394564],
      "type": "Point"
    },
    {
      "name": "34th St - Penn Station",
      "line": "1-2-3",
      "coords": [-73.99105699913983, 40.75037300003949],
      "type": "Point"
    },
    {
      "name": "Times Sq - 42nd St",
      "line": "1-2-3",
      "coords": [-73.98749500051885, 40.75528999995681],
      "type": "Point"
    },
    {
      "name": "Fulton St",
      "line": "A-C",
      "coords": [-74.00762309323994, 40.71016216530185],
      "type": "Point"
    },
    {
      "name": "Chambers St",
      "line": "A-C",
      "coords": [-74.00858473570133, 40.714111000774025],
      "type": "Point"
    },
    {
      "name": "42nd St - Port Authority Bus Term",
      "line": "A-C-E",
      "coords": [-73.98973500085859, 40.757307998551504],
      "type": "Point"
    },
    {
      "name": "Myrtle-Willoughby Aves",
      "line": "G",
      "coords": [-73.94906699890156, 40.69461899903765],
      "type": "Point"
    },
    {
      "name": "Flushing Ave",
      "line": "G",
      "coords": [-73.9502340010257, 40.70037666622154],
      "type": "Point"
    },
    {
      "name": "23rd St",
      "line": "F-M",
      "coords": [-73.99276500471389, 40.742954317826005],
      "type": "Point"
    },
    {
      "name": "Herald Sq - 34th St",
      "line": "B-D-F-M",
      "coords": [-73.98777189072918, 40.74978939990011],
      "type": "Point"
    },
    {
      "name": "Hoyt - Schermerhorn Sts",
      "line": "A-C-G",
      "coords": [-73.98503624034139, 40.68840847580642],
      "type": "Point"
    },
    {
      "name": "Jay St - MetroTech",
      "line": "A-C-F",
      "coords": [-73.98721815267317, 40.692470636847084],
      "type": "Point"
    },
    {
      "name": "East Broadway",
      "line": "F",
      "coords": [-73.99017700122197, 40.713855001020406],
      "type": "Point"
    },
    {
      "name": "Delancey St - Essex St",
      "line": "F",
      "coords": [-73.98807806807719, 40.71868074219453],
      "type": "Point"
    },
    {
      "name": "Lower East Side - 2nd Ave",
      "line": "F",
      "coords": [-73.98993800003434, 40.72340166574911],
      "type": "Point"
    },
    {
      "name": "Flushing Ave",
      "line": "J-M",
      "coords": [-73.94137734838365, 40.70040440298112],
      "type": "Point"
    },
    {
      "name": "Myrtle Ave",
      "line": "J-M-Z",
      "coords": [-73.9356230012996, 40.6971950005145],
      "type": "Point"
    },
    {
      "name": "4th Av - 9th St",
      "line": "F-G",
      "coords": [-73.98977899938897, 40.67027166728493],
      "type": "Point"
    },
    {
      "name": "Smith - 9th Sts",
      "line": "F-G",
      "coords": [-73.99589172790934, 40.67364106090412],
      "type": "Point"
    },
    {
      "name": "Bergen St",
      "line": "F-G",
      "coords": [-73.99075649573565, 40.68611054725977],
      "type": "Point"
    },
    {
      "name": "Jay St - MetroTech",
      "line": "N-R",
      "coords": [-73.98605667854612, 40.69225539645323],
      "type": "Point"
    },
    {
      "name": "Court St",
      "line": "N-R",
      "coords": [-73.99181830901125, 40.694196480776995],
      "type": "Point"
    },
    {
      "name": "Union Sq - 14th St",
      "line": "N-Q-R-W",
      "coords": [-73.99053886181645, 40.73587226699812],
      "type": "Point"
    },
    {
      "name": "23rd St",
      "line": "N-Q-R-W",
      "coords": [-73.98934400102907, 40.74130266729],
      "type": "Point"
    },
    {
      "name": "Prospect Ave",
      "line": "D-N-R",
      "coords": [-73.99287200067424, 40.66541366712979],
      "type": "Point"
    },
    {
      "name": "4th Av - 9th St",
      "line": "D-N-R",
      "coords": [-73.98830199974512, 40.670846666842756],
      "type": "Point"
    },
    {
      "name": "3rd Ave",
      "line": "L",
      "coords": [-73.98575000112093, 40.73269099971662],
      "type": "Point"
    },
    {
      "name": "Union Sq - 14th St",
      "line": "L",
      "coords": [-73.99066976901818, 40.73476331217923],
      "type": "Point"
    },
    {
      "name": "Liberty Ave",
      "line": "A-C",
      "coords": [-73.89654800103929, 40.67454199987086],
      "type": "Point"
    },
    {
      "name": "Broadway Junction",
      "line": "A-C",
      "coords": [-73.90531600055341, 40.67833366608023],
      "type": "Point"
    },
    {
      "name": "59th St",
      "line": "N-R",
      "coords": [-74.01788099953987, 40.6413616662838],
      "type": "Point"
    },
    {
      "name": "45th St",
      "line": "N-R",
      "coords": [-74.01000600074939, 40.648938666612814],
      "type": "Point"
    },
    {
      "name": "36th St",
      "line": "D-N-R",
      "coords": [-74.00354899951809, 40.65514366633887],
      "type": "Point"
    },
    {
      "name": "9th Ave",
      "line": "D",
      "coords": [-73.99444874451204, 40.64648407726636],
      "type": "Point"
    },
    {
      "name": "53rd St",
      "line": "N-R",
      "coords": [-74.01403399986317, 40.64506866735981],
      "type": "Point"
    },
    {
      "name": "Ft Hamilton Pkwy",
      "line": "D",
      "coords": [-73.9942022375285, 40.640912711444656],
      "type": "Point"
    },
    {
      "name": "25th St",
      "line": "D-N-R",
      "coords": [-73.99809099974297, 40.66039666692321],
      "type": "Point"
    },
    {
      "name": "Carroll St",
      "line": "F-G",
      "coords": [-73.99494697998841, 40.68027335170176],
      "type": "Point"
    },
    {
      "name": "Spring St",
      "line": "A-C-E",
      "coords": [-74.00373899843763, 40.72622700129312],
      "type": "Point"
    },
    {
      "name": "181st St",
      "line": "A",
      "coords": [-73.93796900205011, 40.851694999744616],
      "type": "Point"
    },
    {
      "name": "190th St",
      "line": "A",
      "coords": [-73.93417999964333, 40.85902199892482],
      "type": "Point"
    },
    {
      "name": "116th St",
      "line": "A-B-C",
      "coords": [-73.95479778057312, 40.80505813344211],
      "type": "Point"
    },
    {
      "name": "125th St",
      "line": "A-B-C-D",
      "coords": [-73.95224799734774, 40.811071672994565],
      "type": "Point"
    },
    {
      "name": "Prince St",
      "line": "N-Q-R-W",
      "coords": [-73.99770200045987, 40.72432866597571],
      "type": "Point"
    },
    {
      "name": "8th St - NYU",
      "line": "N-Q-R-W",
      "coords": [-73.99250799849149, 40.73046499853991],
      "type": "Point"
    },
    {
      "name": "Fulton St",
      "line": "2-3",
      "coords": [-74.00657099970202, 40.70941599925865],
      "type": "Point"
    },
    {
      "name": "Park Pl",
      "line": "2-3",
      "coords": [-74.00881099997359, 40.713050999077694],
      "type": "Point"
    },
    {
      "name": "Chambers St",
      "line": "1-2-3",
      "coords": [-74.00926600170112, 40.71547800011327],
      "type": "Point"
    },
    {
      "name": "Hoyt St",
      "line": "2-3",
      "coords": [-73.98506379575646, 40.69054418535472],
      "type": "Point"
    },
    {
      "name": "Borough Hall",
      "line": "2-3",
      "coords": [-73.98999799960687, 40.693218999611084],
      "type": "Point"
    },
    {
      "name": "183rd St",
      "line": "4",
      "coords": [-73.90387900151532, 40.85840700040842],
      "type": "Point"
    },
    {
      "name": "Fordham Rd",
      "line": "4",
      "coords": [-73.90103399921699, 40.86280299988937],
      "type": "Point"
    },
    {
      "name": "World Trade Center",
      "line": "E",
      "coords": [-74.00974461517701, 40.71256392680817],
      "type": "Point"
    },
    {
      "name": "Canal St - Holland Tunnel",
      "line": "A-C-E",
      "coords": [-74.0052290023424, 40.72082400007119],
      "type": "Point"
    },
    {
      "name": "155th St",
      "line": "A-C",
      "coords": [-73.94151400082208, 40.83051799929251],
      "type": "Point"
    },
    {
      "name": "163rd St - Amsterdam Av",
      "line": "A-C",
      "coords": [-73.93989200188344, 40.83601299923096],
      "type": "Point"
    },
    {
      "name": "Fulton St",
      "line": "J-Z",
      "coords": [-74.00793800110387, 40.71002266658424],
      "type": "Point"
    },
    {
      "name": "Chambers St",
      "line": "J-Z",
      "coords": [-74.00340673031336, 40.71323378962671],
      "type": "Point"
    },
    {
      "name": "Canal St",
      "line": "J-Z",
      "coords": [-73.99982638545937, 40.71817387697391],
      "type": "Point"
    },
    {
      "name": "City Hall",
      "line": "R-W",
      "coords": [-74.00698581780337, 40.71327233111697],
      "type": "Point"
    },
    {
      "name": "Canal St",
      "line": "R-W",
      "coords": [-74.0018260000577, 40.71946500105898],
      "type": "Point"
    },
    {
      "name": "South Ferry",
      "line": "1",
      "coords": [-74.01316895919258, 40.701730507574474],
      "type": "Point"
    },
    {
      "name": "Bowling Green",
      "line": "4-5",
      "coords": [-74.01400799803432, 40.70491399928076],
      "type": "Point"
    },
    {
      "name": "Wall St",
      "line": "4-5",
      "coords": [-74.01186199860112, 40.70755700086603],
      "type": "Point"
    },
    {
      "name": "Whitehall St",
      "line": "R-W",
      "coords": [-74.0130072374272, 40.703142373599135],
      "type": "Point"
    },
    {
      "name": "Rector St",
      "line": "R-W",
      "coords": [-74.01297456253795, 40.707744756294474],
      "type": "Point"
    },
    {
      "name": "Fresh Pond Rd",
      "line": "M",
      "coords": [-73.8958980017196, 40.70622599823048],
      "type": "Point"
    },
    {
      "name": "Middle Village - Metropolitan Ave",
      "line": "M",
      "coords": [-73.88957722978091, 40.711431305058255],
      "type": "Point"
    },
    {
      "name": "Rector St",
      "line": "1",
      "coords": [-74.01378300119742, 40.707512999521775],
      "type": "Point"
    },
    {
      "name": "Cortlandt St",
      "line": "1",
      "coords": [-74.01218800112292, 40.7118350008202],
      "type": "Point"
    },
    {
      "name": "Fulton St",
      "line": "4-5",
      "coords": [-74.00950899856461, 40.710367998822136],
      "type": "Point"
    },
    {
      "name": "Broad St",
      "line": "J-Z",
      "coords": [-74.01105599991755, 40.706476001106005],
      "type": "Point"
    },
    {
      "name": "Cortlandt St",
      "line": "R-W",
      "coords": [-74.01113196473266, 40.7105129841524],
      "type": "Point"
    },
    {
      "name": "Wall St",
      "line": "2-3",
      "coords": [-74.00909999844257, 40.706820999753376],
      "type": "Point"
    },
    {
      "name": "Dyckman St",
      "line": "A",
      "coords": [-73.92727099960726, 40.865490998968916],
      "type": "Point"
    },
    {
      "name": "Grand St",
      "line": "B-D",
      "coords": [-73.99375299913589, 40.71826699954992],
      "type": "Point"
    },
    {
      "name": "Broadway - Lafayette St",
      "line": "B-D-F-M",
      "coords": [-73.99620399876055, 40.725296998738045],
      "type": "Point"
    },
    {
      "name": "Bowery",
      "line": "J-Z",
      "coords": [-73.99380690654237, 40.720246883147254],
      "type": "Point"
    },
    {
      "name": "Canal St",
      "line": "N-Q",
      "coords": [-74.00105471306033, 40.718814263587134],
      "type": "Point"
    },
    {
      "name": "23rd St",
      "line": "A-C-E",
      "coords": [-73.99804100117201, 40.74590599939995],
      "type": "Point"
    },
    {
      "name": "34th St - Penn Station",
      "line": "A-C-E",
      "coords": [-73.99339099970578, 40.752287000775894],
      "type": "Point"
    },
    {
      "name": "Jackson Hts - Roosevelt Av",
      "line": "E-F-M-R",
      "coords": [-73.89129866519697, 40.74653969115889],
      "type": "Point"
    },
    {
      "name": "14th St",
      "line": "1-2-3",
      "coords": [-74.00020100063497, 40.737825999728116],
      "type": "Point"
    },
    {
      "name": "135th St",
      "line": "A-B-C",
      "coords": [-73.94753480879213, 40.817905559212676],
      "type": "Point"
    },
    {
      "name": "14th St",
      "line": "F-M",
      "coords": [-73.99620899921355, 40.73822799969515],
      "type": "Point"
    },
    {
      "name": "6th Ave",
      "line": "L",
      "coords": [-73.99775078874781, 40.73774146981052],
      "type": "Point"
    },
    {
      "name": "8th Ave",
      "line": "L",
      "coords": [-74.00257800104762, 40.73977666638199],
      "type": "Point"
    },
    {
      "name": "14th St",
      "line": "A-C-E",
      "coords": [-74.00168999937027, 40.740893000193296],
      "type": "Point"
    },
    {
      "name": "Nostrand Ave",
      "line": "3-4",
      "coords": [-73.9504262489579, 40.66993815093054],
      "type": "Point"
    },
    {
      "name": "Clark St",
      "line": "2-3",
      "coords": [-73.99308599821961, 40.69746599996469],
      "type": "Point"
    },
    {
      "name": "Franklin Ave",
      "line": "A-C",
      "coords": [-73.95684800014614, 40.68137966658742],
      "type": "Point"
    },
    {
      "name": "Clinton - Washington Aves",
      "line": "A-C",
      "coords": [-73.96583799857275, 40.68326299912644],
      "type": "Point"
    },
    {
      "name": "Forest Ave",
      "line": "M",
      "coords": [-73.90307500005954, 40.70441200087814],
      "type": "Point"
    },
    {
      "name": "110th St",
      "line": "4-6-6 Express",
      "coords": [-73.94424999687163, 40.795020000113105],
      "type": "Point"
    },
    {
      "name": "86th St",
      "line": "4-5-6-6 Express",
      "coords": [-73.95558899985132, 40.77949199820952],
      "type": "Point"
    },
    {
      "name": "York St",
      "line": "F",
      "coords": [-73.98688499993673, 40.699742667691574],
      "type": "Point"
    },
    {
      "name": "High St",
      "line": "A-C",
      "coords": [-73.99053100065458, 40.69933699977884],
      "type": "Point"
    },
    {
      "name": "Lafayette Ave",
      "line": "A-C",
      "coords": [-73.97394599849406, 40.68611300020567],
      "type": "Point"
    },
    {
      "name": "President St",
      "line": "2-5",
      "coords": [-73.95058920022207, 40.667883603536815],
      "type": "Point"
    },
    {
      "name": "Woodlawn",
      "line": "4",
      "coords": [-73.87875099990931, 40.886037000253324],
      "type": "Point"
    },
    {
      "name": "Bleecker St",
      "line": "4-6-6 Express",
      "coords": [-73.99465900006331, 40.72591466682659],
      "type": "Point"
    },
    {
      "name": "103rd St",
      "line": "4-6-6 Express",
      "coords": [-73.94747800152219, 40.79060000008452],
      "type": "Point"
    },
    {
      "name": "Euclid Ave",
      "line": "A-C-S",
      "coords": [-73.87210600099675, 40.675376998239365],
      "type": "Point"
    },
    {
      "name": "88th St",
      "line": "A-S",
      "coords": [-73.85147000026086, 40.67984300135503],
      "type": "Point"
    },
    {
      "name": "Cortelyou Rd",
      "line": "Q",
      "coords": [-73.96379005505493, 40.6409401651401],
      "type": "Point"
    },
    {
      "name": "116th St",
      "line": "4-6-6 Express",
      "coords": [-73.9416169983714, 40.7986290002001],
      "type": "Point"
    },
    {
      "name": "Parkchester",
      "line": "6-6 Express",
      "coords": [-73.86081600108396, 40.83322599927859],
      "type": "Point"
    },
    {
      "name": "Franklin St",
      "line": "1-2",
      "coords": [-74.00688600277107, 40.719318001302135],
      "type": "Point"
    },
    {
      "name": "80th St",
      "line": "A-S",
      "coords": [-73.85899200206335, 40.67937100115432],
      "type": "Point"
    },
    {
      "name": "5th Ave - Bryant Pk",
      "line": "7-7 Express",
      "coords": [-73.98196299856706, 40.75382100064824],
      "type": "Point"
    },
    {
      "name": "Spring St",
      "line": "4-6-6 Express",
      "coords": [-73.99714100006673, 40.72230099999366],
      "type": "Point"
    },
    {
      "name": "125th St",
      "line": "4-5-6-6 Express",
      "coords": [-73.93759400055725, 40.804138000587244],
      "type": "Point"
    },
    {
      "name": "Coney Island - Stillwell Av",
      "line": "D-F-N-Q",
      "coords": [-73.9812359981396, 40.57728100006751],
      "type": "Point"
    },
    {
      "name": "34th St - Hudson Yards",
      "line": "7-7 Express",
      "coords": [-74.00219709442206, 40.75544635961596],
      "type": "Point"
    },
    {
      "name": "72nd St",
      "line": "Q",
      "coords": [-73.95836178682246, 40.76880251014895],
      "type": "Point"
    },
    {
      "name": "86th St",
      "line": "Q",
      "coords": [-73.95177090964917, 40.77786104333163],
      "type": "Point"
    },
    {
      "name": "96th St",
      "line": "Q",
      "coords": [-73.9470660219183, 40.784236650177654],
      "type": "Point"
    }
  ]
}
